shreport/__init__.py
shreport/codename.py
shreport/sh.py
shreport-0.1.3.dist-info/METADATA
shreport-0.1.3.dist-info/WHEEL
shreport-0.1.3.dist-info/top_level.txt
shreport-0.1.3.dist-info/RECORD
