Metadata-Version: 2.1
Name: shreport
Version: 0.1.3
Summary: 上海证券交易所上市公司定期报告下载,项目地址 https://github.com/thunderhit/shreport
Home-page: https://github.com/thunderhit/shreport
Author: 大邓
Author-email: thunderhit@qq.com
License: MIT
Keywords: data collect,数据采集,text analysis,文本分析,pdf download,金融,finance
Platform: UNKNOWN
Requires-Python: >=3.5
Requires-Dist: requests
Requires-Dist: grequests
